timetoc/__init__.py
timetoc/cli.py
timetoc/login.py
timetoc/timeparser.py
timetoc/timetracking.py
timetoc-0.1.2.dist-info/WHEEL
timetoc-0.1.2.dist-info/entry_points.txt
timetoc-0.1.2.dist-info/METADATA
timetoc-0.1.2.dist-info/RECORD
