Metadata-Version: 2.1
Name: timetoc
Version: 0.1.2
Summary: 
Author: Guilherme Prokisch
Author-email: guilherme.prokisch@gmail.com
Requires-Python: >=3.10,<4.0
Classifier: Programming Language :: Python :: 3
Classifier: Programming Language :: Python :: 3.10
Classifier: Programming Language :: Python :: 3.11
Requires-Dist: holidays (>=0.21.13,<0.22.0)
Requires-Dist: pandas (>=1.5.3,<2.0.0)
Requires-Dist: python-dateutil (>=2.8.2,<3.0.0)
Requires-Dist: requests (>=2.28.2,<3.0.0)
Requires-Dist: selenium-wire (>=5.1.0,<6.0.0)
Requires-Dist: typer[all] (>=0.7.0,<0.8.0)
Requires-Dist: webdriver-manager (>=3.8.5,<4.0.0)
